{"resource":"teamdashboardbygeneralsplits","parameters":{"MeasureType":"Advanced","PerMode":"PerGame","PlusMinus":"N","PaceAdjust":"N","Rank":"N","LeagueID":"00","Season":"2018-19","SeasonType":"Regular Season","PORound":0,"TeamID":1610612758,"Outcome":null,"Location":null,"Month":0,"SeasonSegment":null,"DateFrom":null,"DateTo":null,"OpponentTeamID":0,"VsConference":null,"VsDivision":null,"GameSegment":null,"Period":0,"ShotClockRange":null,"LastNGames":0},"resultSets":[{"name":"OverallTeamDashboard","headers":["GROUP_SET","GROUP_VALUE","SEASON_YEAR","GP","W","L","W_PCT","MIN","E_OFF_RATING","OFF_RATING","E_DEF_RATING","DEF_RATING","E_NET_RATING","NET_RATING","AST_PCT","AST_TO","AST_RATIO","OREB_PCT","DREB_PCT","REB_PCT","TM_TOV_PCT","EFG_PCT","TS_PCT","E_PACE","PACE","PIE","GP_RANK","W_RANK","L_RANK","W_PCT_RANK","MIN_RANK","OFF_RATING_RANK","DEF_RATING_RANK","NET_RATING_RANK","AST_PCT_RANK","AST_TO_RANK","AST_RATIO_RANK","OREB_PCT_RANK","DREB_PCT_RANK","REB_PCT_RANK","TM_TOV_PCT_RANK","EFG_PCT_RANK","TS_PCT_RANK","PACE_RANK","PIE_RANK","CFID","CFPARAMS"],"rowSet":[["Overall","2018-19","2018-19",22,11,11,0.500000,1056.0,107.2,107.9,108.4,110.5,-1.2,-2.5,0.567,1.66,17.3,0.251,0.711,0.481,0.141,0.533,0.559,107.4,105.98,0.487,1,1,1,1,1,1,1,1,1,1,1,1,1,1,1,1,1,1,1,155,"2018-19"]]},{"name":"LocationTeamDashboard","headers":["GROUP_SET","GROUP_VALUE","TEAM_GAME_LOCATION","GP","W","L","W_PCT","MIN","E_OFF_RATING","OFF_RATING","E_DEF_RATING","DEF_RATING","E_NET_RATING","NET_RATING","AST_PCT","AST_TO","AST_RATIO","OREB_PCT","DREB_PCT","REB_PCT","TM_TOV_PCT","EFG_PCT","TS_PCT","E_PACE","PACE","PIE","GP_RANK","W_RANK","L_RANK","W_PCT_RANK","MIN_RANK","OFF_RATING_RANK","DEF_RATING_RANK","NET_RATING_RANK","AST_PCT_RANK","AST_TO_RANK","AST_RATIO_RANK","OREB_PCT_RANK","DREB_PCT_RANK","REB_PCT_RANK","TM_TOV_PCT_RANK","EFG_PCT_RANK","TS_PCT_RANK","PACE_RANK","PIE_RANK","CFID","CFPARAMS"],"rowSet":[["Location","Home","Home",11,6,5,0.545000,528.0,103.7,103.9,104.6,107.0,-0.8,-3.1,0.546,1.49,16.2,0.256,0.721,0.487,0.145,0.51,0.54,106.8,105.5,0.487,1,1,1,1,1,2,1,2,2,2,2,1,1,1,2,2,2,2,1,153,"Home"],["Location","Road","Road",11,5,6,0.455000,528.0,110.5,112.0,112.2,113.9,-1.7,-1.9,0.587,1.83,18.4,0.245,0.701,0.474,0.138,0.556,0.578,108.0,106.45,0.487,1,2,2,2,1,1,2,1,1,1,1,2,2,2,1,1,1,1,2,153,"Road"]]},{"name":"WinsLossesTeamDashboard","headers":["GROUP_SET","GROUP_VALUE","GAME_RESULT","GP","W","L","W_PCT","MIN","E_OFF_RATING","OFF_RATING","E_DEF_RATING","DEF_RATING","E_NET_RATING","NET_RATING","AST_PCT","AST_TO","AST_RATIO","OREB_PCT","DREB_PCT","REB_PCT","TM_TOV_PCT","EFG_PCT","TS_PCT","E_PACE","PACE","PIE","GP_RANK","W_RANK","L_RANK","W_PCT_RANK","MIN_RANK","OFF_RATING_RANK","DEF_RATING_RANK","NET_RATING_RANK","AST_PCT_RANK","AST_TO_RANK","AST_RATIO_RANK","OREB_PCT_RANK","DREB_PCT_RANK","REB_PCT_RANK","TM_TOV_PCT_RANK","EFG_PCT_RANK","TS_PCT_RANK","PACE_RANK","PIE_RANK","CFID","CFPARAMS"],"rowSet":[["Wins/Losses","Wins","Wins",11,11,0,1.000000,528.0,109.8,110.5,99.7,101.9,10.1,8.6,0.598,1.71,18.3,0.261,0.72,0.5,0.146,0.547,0.572,107.9,106.36,0.556,1,1,1,1,1,1,1,1,1,1,1,1,1,1,2,1,1,1,1,157,"Wins"],["Wins/Losses","Losses","Losses",11,0,11,0.000000,528.0,104.5,105.3,117.2,119.1,-12.7,-13.8,0.535,1.59,16.3,0.241,0.701,0.46,0.136,0.519,0.546,106.9,105.59,0.422,1,2,2,2,1,2,2,2,2,2,2,2,2,2,1,2,2,2,2,157,"Losses"]]},{"name":"MonthTeamDashboard","headers":["GROUP_SET","GROUP_VALUE","SEASON_MONTH_NAME","GP","W","L","W_PCT","MIN","E_OFF_RATING","OFF_RATING","E_DEF_RATING","DEF_RATING","E_NET_RATING","NET_RATING","AST_PCT","AST_TO","AST_RATIO","OREB_PCT","DREB_PCT","REB_PCT","TM_TOV_PCT","EFG_PCT","TS_PCT","E_PACE","PACE","PIE","GP_RANK","W_RANK","L_RANK","W_PCT_RANK","MIN_RANK","OFF_RATING_RANK","DEF_RATING_RANK","NET_RATING_RANK","AST_PCT_RANK","AST_TO_RANK","AST_RATIO_RANK","OREB_PCT_RANK","DREB_PCT_RANK","REB_PCT_RANK","TM_TOV_PCT_RANK","EFG_PCT_RANK","TS_PCT_RANK","PACE_RANK","PIE_RANK","CFID","CFPARAMS"],"rowSet":[["Month","October","October",8,5,3,0.625000,384.0,108.8,109.0,106.9,108.6,1.9,0.4,0.53,1.56,16.9,0.233,0.71,0.479,0.144,0.553,0.572,108.1,107.19,0.504,2,1,2,2,2,1,2,1,3,2,3,3,2,2,2,1,1,1,1,154,"October"],["Month","November","November",13,5,8,0.385000,624.0,106.4,107.6,109.9,112.1,-3.4,-4.5,0.588,1.76,17.6,0.256,0.707,0.479,0.136,0.522,0.552,106.9,105.19,0.477,1,1,3,3,1,2,3,3,2,1,1,2,3,3,1,2,2,3,3,154,"November"],["Month","December","December",1,1,0,1.000000,48.0,103.2,103.7,101.0,103.8,2.2,0.0,0.61,1.25,17.0,0.321,0.786,0.526,0.187,0.522,0.546,108.2,106.5,0.479,3,3,1,1,3,3,1,2,1,3,2,1,1,1,3,3,3,2,2,154,"December"]]},{"name":"PrePostAllStarTeamDashboard","headers":["GROUP_SET","GROUP_VALUE","SEASON_SEGMENT","GP","W","L","W_PCT","MIN","E_OFF_RATING","OFF_RATING","E_DEF_RATING","DEF_RATING","E_NET_RATING","NET_RATING","AST_PCT","AST_TO","AST_RATIO","OREB_PCT","DREB_PCT","REB_PCT","TM_TOV_PCT","EFG_PCT","TS_PCT","E_PACE","PACE","PIE","GP_RANK","W_RANK","L_RANK","W_PCT_RANK","MIN_RANK","OFF_RATING_RANK","DEF_RATING_RANK","NET_RATING_RANK","AST_PCT_RANK","AST_TO_RANK","AST_RATIO_RANK","OREB_PCT_RANK","DREB_PCT_RANK","REB_PCT_RANK","TM_TOV_PCT_RANK","EFG_PCT_RANK","TS_PCT_RANK","PACE_RANK","PIE_RANK","CFID","CFPARAMS"],"rowSet":[["Pre/Post All-Star","Pre All-Star","Pre All-Star",22,11,11,0.500000,1056.0,107.2,107.9,108.4,110.5,-1.2,-2.5,0.567,1.66,17.3,0.251,0.711,0.481,0.141,0.533,0.559,107.4,105.98,0.487,1,1,1,1,1,1,1,1,1,1,1,1,1,1,1,1,1,1,1,156,"Pre All-Star"]]},{"name":"DaysRestTeamDashboard","headers":["GROUP_SET","GROUP_VALUE","TEAM_DAYS_REST_RANGE","GP","W","L","W_PCT","MIN","E_OFF_RATING","OFF_RATING","E_DEF_RATING","DEF_RATING","E_NET_RATING","NET_RATING","AST_PCT","AST_TO","AST_RATIO","OREB_PCT","DREB_PCT","REB_PCT","TM_TOV_PCT","EFG_PCT","TS_PCT","E_PACE","PACE","PIE","GP_RANK","W_RANK","L_RANK","W_PCT_RANK","MIN_RANK","OFF_RATING_RANK","DEF_RATING_RANK","NET_RATING_RANK","AST_PCT_RANK","AST_TO_RANK","AST_RATIO_RANK","OREB_PCT_RANK","DREB_PCT_RANK","REB_PCT_RANK","TM_TOV_PCT_RANK","EFG_PCT_RANK","TS_PCT_RANK","PACE_RANK","PIE_RANK","CFID","CFPARAMS"],"rowSet":[["Days Rest","0 Days Rest","0 Days Rest",5,2,3,0.400000,240.0,97.8,98.1,104.3,106.5,-6.5,-8.4,0.49,1.16,13.9,0.257,0.7,0.478,0.156,0.48,0.514,106.0,104.7,0.453,2,2,4,2,2,5,1,4,4,5,4,2,5,3,4,5,5,4,3,152,"0 Days Rest"],["Days Rest","1 Days Rest","1 Days Rest",10,8,2,0.800000,480.0,112.2,113.1,106.5,108.8,5.6,4.3,0.601,1.8,18.9,0.254,0.706,0.486,0.144,0.563,0.585,108.4,106.8,0.527,1,1,2,1,1,1,2,1,2,3,1,3,3,2,3,1,1,3,1,152,"1 Days Rest"],["Days Rest","2 Days Rest","2 Days Rest",4,1,3,0.250000,192.0,104.3,105.6,111.8,113.2,-7.5,-7.6,0.615,2.06,18.3,0.216,0.7,0.45,0.121,0.521,0.541,108.8,107.5,0.449,3,3,4,3,3,4,3,3,1,1,2,4,4,5,2,4,4,2,4,152,"2 Days Rest"],["Days Rest","3 Days Rest","3 Days Rest",2,0,2,0.000000,96.0,109.8,110.8,118.4,121.9,-8.7,-11.1,0.59,1.53,17.3,0.351,0.758,0.548,0.158,0.526,0.568,103.0,101.0,0.455,4,4,2,4,4,2,5,5,3,4,3,1,2,1,5,3,3,5,2,152,"3 Days Rest"],["Days Rest","4 Days Rest","4 Days Rest",1,0,1,0.000000,48.0,109.4,108.3,114.2,113.9,-4.8,-5.6,0.347,1.89,12.9,0.143,0.795,0.452,0.083,0.553,0.568,107.3,108.0,0.447,5,4,1,4,5,3,4,2,5,2,5,5,1,4,1,2,2,1,5,152,"4 Days Rest"]]}]}